opensqli/__init__.py
opensqli/__main__.py
opensqli/cli.py
opensqli/scanner.py
opensqli/utils.py
opensqli-0.1.6.dist-info/entry_points.txt
opensqli-0.1.6.dist-info/WHEEL
opensqli-0.1.6.dist-info/METADATA
opensqli-0.1.6.dist-info/RECORD
